upcat/__init__.py
upcat/cli.py
upcat/main.py
upcat-0.1.0.dist-info/LICENSE
upcat-0.1.0.dist-info/METADATA
upcat-0.1.0.dist-info/WHEEL
upcat-0.1.0.dist-info/entry_points.txt
upcat-0.1.0.dist-info/top_level.txt
upcat-0.1.0.dist-info/RECORD
