Metadata-Version: 2.1
Name: upcat
Version: 0.1.0
Summary: 图片文件夹可视化工具
Home-page: https://github.com/upcat-project/upcat
Author: upcat Authors
Author-email: upcat@example.com
License: MIT
Platform: UNKNOWN
Classifier: Programming Language :: Python :: 3
Classifier: License :: OSI Approved :: MIT License
Classifier: Operating System :: OS Independent
Classifier: Intended Audience :: End Users/Desktop
Classifier: Topic :: Multimedia :: Graphics
Classifier: Topic :: Utilities
Requires-Python: >=3.6
